gps_tools/__init__.py
gps_tools_pkg-0.1.2.dist-info/LICENSE
gps_tools_pkg-0.1.2.dist-info/METADATA
gps_tools_pkg-0.1.2.dist-info/WHEEL
gps_tools_pkg-0.1.2.dist-info/top_level.txt
gps_tools_pkg-0.1.2.dist-info/RECORD
